gpu_queue/__init__.py
gpu_queue/main.py
gpu_queue/stdout_writer.py
GPUQueue-0.0.3.dist-info/METADATA
GPUQueue-0.0.3.dist-info/WHEEL
GPUQueue-0.0.3.dist-info/entry_points.txt
GPUQueue-0.0.3.dist-info/top_level.txt
GPUQueue-0.0.3.dist-info/RECORD
