Metadata-Version: 2.1
Name: GPUQueue
Version: 0.0.3
Summary: UNKNOWN
Home-page: https://github.com/jizongFox/GPUQueues
Author: jizong
Author-email: jizong.peng.1@etsmtl.net
License: MIT
Platform: UNKNOWN
Classifier: License :: OSI Approved :: MIT License
Classifier: Programming Language :: Python :: 3
Classifier: Programming Language :: Python :: 3.7
